currentscope/__init__.py
currentscope-0.1.0a0.dist-info/LICENSE
currentscope-0.1.0a0.dist-info/METADATA
currentscope-0.1.0a0.dist-info/WHEEL
currentscope-0.1.0a0.dist-info/RECORD
