Metadata-Version: 2.1
Name: currentscope
Version: 0.1.0a0
Summary: CurrentScope Python API
License: MIT
Author: currentscope
Author-email: reach@currentscope.co.uk
Requires-Python: >=3.11,<4.0
Classifier: License :: OSI Approved :: MIT License
Classifier: Programming Language :: Python :: 3
Classifier: Programming Language :: Python :: 3.11
Classifier: Programming Language :: Python :: 3.12
